dubplate/__init__.py
dubplate-0.2.0.dist-info/LICENSE
dubplate-0.2.0.dist-info/METADATA
dubplate-0.2.0.dist-info/WHEEL
dubplate-0.2.0.dist-info/top_level.txt
dubplate-0.2.0.dist-info/RECORD
